README.md
config.py
setup.py
standalone.py
arat.egg-info/PKG-INFO
arat.egg-info/SOURCES.txt
arat.egg-info/dependency_links.txt
arat.egg-info/not-zip-safe
arat.egg-info/requires.txt
arat.egg-info/top_level.txt
server/__init__.py
server/annlog.py
server/annotator.py
server/arat_server.py
server/aratlex.py
server/aratyacc.py
server/auth.py
server/backup.py
server/common.py
server/constants.py
server/delete.py
server/dispatch.py
server/docimport.py
server/document.py
server/download.py
server/filelock.py
server/gtbtokenize.py
server/jsonwrap.py
server/mecab.py
server/message.py
server/normdb.py
server/predict.py
server/sdistance.py
server/search.py
server/session.py
server/ssplit.py
server/sspostproc.py
server/stats.py
server/svg.py
server/tag.py
server/tokenise.py
server/undo.py
server/verify_annotations.py