Metadata-Version: 1.1
Name: arat
Version: 0.0
Summary: Arat annotation tool
Home-page: https://github.com/neophnx/arat/
Author: neophnx
Author-email: UNKNOWN
License: MIT
Platform: UNKNOWN
Classifier: Programming Language :: Python
Classifier: Development Status :: 1 - Planning
Classifier: License :: OSI Approved
Classifier: Programming Language :: Python :: 2.7
Classifier: Programming Language :: Python :: 3.5
Classifier: Programming Language :: Python :: 3.6
